_bitarray.cpython-39-darwin.so
_crypto.cpython-39-darwin.so
_secp256k1.cpython-39-darwin.so
_sha3_hash.cpython-39-darwin.so
cache_strategies.cpython-39-darwin.so
pybtc/__init__.py
pybtc/consensus.py
pybtc/constants.py
pybtc/crypto.py
pybtc/opcodes.py
pybtc/bip39_word_list/chinese_simplified.txt
pybtc/bip39_word_list/chinese_traditional.txt
pybtc/bip39_word_list/english.txt
pybtc/bip39_word_list/french.txt
pybtc/bip39_word_list/italian.txt
pybtc/bip39_word_list/japanese.txt
pybtc/bip39_word_list/korean.txt
pybtc/bip39_word_list/spanish.txt
pybtc/bitarray/__init__.py
pybtc/classes/__init__.py
pybtc/classes/address.py
pybtc/classes/block.py
pybtc/classes/transaction.py
pybtc/classes/wallet.py
pybtc/connector/__init__.py
pybtc/connector/block_loader.py
pybtc/connector/connector.py
pybtc/connector/utils.py
pybtc/connector/utxo.py
pybtc/functions/__init__.py
pybtc/functions/address.py
pybtc/functions/bip32.py
pybtc/functions/bip39_mnemonic.py
pybtc/functions/block.py
pybtc/functions/encode.py
pybtc/functions/entropy.py
pybtc/functions/filters.py
pybtc/functions/hash.py
pybtc/functions/key.py
pybtc/functions/script.py
pybtc/functions/shamir.py
pybtc/functions/tools.py
test/__init__.py
test/address_class.py
test/address_functions.py
test/block.py
test/create_transaction.py
test/ecdsa.py
test/filters.py
test/hash_functions.py
test/integer.py
test/mnemonic.py
test/script_deserialize.py
test/script_functions.py
test/shamir.py
test/sighash.py
test/transaction_constructor.py
test/transaction_deserialize.py
test/wallet_class.py
tests/__init__.py
tests/conftest.py
tests/test_address_functions.py
tests/test_bip32_functions.py
tests/test_bip39_mnemonic_functions.py
tests/test_block_functions.py
tests/test_encoders_functions.py
tests/test_hash_functions.py
tests/test_key_functions.py
tests/test_script_functions.py
tests/test_shamir_functions.py
tests/test_tools_functions.py
tests/test_wallet_class.py
pybtc-2.3.11.dist-info/LICENSE
pybtc-2.3.11.dist-info/METADATA
pybtc-2.3.11.dist-info/WHEEL
pybtc-2.3.11.dist-info/top_level.txt
pybtc-2.3.11.dist-info/RECORD
